pyqg_jax/__init__.py
pyqg_jax/_kernel.py
pyqg_jax/_model.py
pyqg_jax/_spectral.py
pyqg_jax/_utils.py
pyqg_jax/bt_model.py
pyqg_jax/diagnostics.py
pyqg_jax/qg_model.py
pyqg_jax/sqg_model.py
pyqg_jax/state.py
pyqg_jax/steppers.py
pyqg_jax/parameterizations/__init__.py
pyqg_jax/parameterizations/_defs.py
pyqg_jax/parameterizations/_parameterized_model.py
pyqg_jax/parameterizations/backscatterbiharmonic.py
pyqg_jax/parameterizations/noop.py
pyqg_jax/parameterizations/smagorinsky.py
pyqg_jax/parameterizations/zannabolton2020.py
pyqg_jax-0.8.1.dist-info/LICENSE.txt
pyqg_jax-0.8.1.dist-info/WHEEL
pyqg_jax-0.8.1.dist-info/METADATA
pyqg_jax-0.8.1.dist-info/RECORD
