Metadata-Version: 2.1
Name: pyqg-jax
Version: 0.8.1
Summary: Quasigeostrophic model in JAX (port of PyQG)
Author: Karl Otness
Requires-Python: >=3.9
Classifier: Development Status :: 2 - Pre-Alpha
Classifier: License :: OSI Approved :: MIT License
Classifier: Operating System :: OS Independent
Classifier: Intended Audience :: Science/Research
Classifier: Topic :: Scientific/Engineering
Classifier: Topic :: Scientific/Engineering :: Atmospheric Science
Classifier: Topic :: Scientific/Engineering :: Oceanography
Classifier: Topic :: Scientific/Engineering :: Physics
Classifier: Programming Language :: Python
Classifier: Programming Language :: Python :: 3
Classifier: Programming Language :: Python :: 3 :: Only
Classifier: Programming Language :: Python :: 3.9
Classifier: Programming Language :: Python :: 3.10
Classifier: Programming Language :: Python :: 3.11
Classifier: Programming Language :: Python :: 3.12
Requires-Dist: jax>=0.4.6
Project-URL: Bug Tracker, https://github.com/karlotness/pyqg-jax/issues
Project-URL: Documentation, https://pyqg-jax.readthedocs.io
Project-URL: Homepage, https://github.com/karlotness/pyqg-jax
Project-URL: Source Code, https://github.com/karlotness/pyqg-jax
